code/__init__.py
code/test.py
tianwei6688-1.0.dist-info/LICENSE
tianwei6688-1.0.dist-info/METADATA
tianwei6688-1.0.dist-info/WHEEL
tianwei6688-1.0.dist-info/top_level.txt
tianwei6688-1.0.dist-info/RECORD
