Metadata-Version: 2.1
Name: tianwei6688
Version: 1.0
Summary: test
Author: tianwei
Author-email: 1784526116@qq.com
Classifier: Programming Language :: Python :: 3
Classifier: License :: OSI Approved :: MIT License
Classifier: Operating System :: OS Independent
Requires-Python: >=3
License-File: LICENSE
Requires-Dist: pillow
